pydatabasecli/__init__.py
pydatabasecli/cli.py
pydatabasecli/const.py
pydatabasecli/db.py
pydatabasecli/exceptions.py
py_database_cli-0.1.1.dist-info/LICENSE
py_database_cli-0.1.1.dist-info/METADATA
py_database_cli-0.1.1.dist-info/WHEEL
py_database_cli-0.1.1.dist-info/entry_points.txt
py_database_cli-0.1.1.dist-info/top_level.txt
py_database_cli-0.1.1.dist-info/RECORD
